{
  "db_name": "PostgreSQL",
  "query": "INSERT INTO magic_link_tokens (user_id, email, token_hash, purpose, expires_at)\n               VALUES ($1, $2, $3, ($4::text)::magic_link_purpose, $5)\n               RETURNING id",
  "describe": {
    "columns": [
      {
        "ordinal": 0,
        "name": "id",
        "type_info": "Uuid",
        "origin": {
          "Table": {
            "table": "magic_link_tokens",
            "name": "id"
          }
        }
      }
    ],
    "parameters": {
      "Left": [
        "Uuid",
        {
          "Custom": {
            "name": "citext",
            "kind": "Simple"
          }
        },
        "Bytea",
        "Text",
        "Timestamptz"
      ]
    },
    "nullable": [
      false
    ]
  },
  "hash": "343ff97475e9d9afcd9ebfcf94fce6964f090586d3d1a3b367b4b12a23675acd"
}
