{
  "db_name": "PostgreSQL",
  "query": "INSERT INTO persons\n               (family_id, given_name, family_name, name_at_birth, nickname, gender,\n                birth_date, birth_place, death_date, notes,\n                email, phone, street, house_number, zip, city, country,\n                linked_user_id)\n               VALUES ($1, $2, $3, $4, $5, $6, $7, $8, $9, $10,\n                       $11, $12, $13, $14, $15, $16, $17, $18)\n               RETURNING id, family_id, given_name, family_name, name_at_birth, nickname,\n                         gender, birth_date, birth_place, death_date, notes,\n                         email, phone, street, house_number, zip, city, country,\n                         linked_user_id, created_at, updated_at",
  "describe": {
    "columns": [
      {
        "ordinal": 0,
        "name": "id",
        "type_info": "Uuid"
      },
      {
        "ordinal": 1,
        "name": "family_id",
        "type_info": "Uuid"
      },
      {
        "ordinal": 2,
        "name": "given_name",
        "type_info": "Text"
      },
      {
        "ordinal": 3,
        "name": "family_name",
        "type_info": "Text"
      },
      {
        "ordinal": 4,
        "name": "name_at_birth",
        "type_info": "Text"
      },
      {
        "ordinal": 5,
        "name": "nickname",
        "type_info": "Text"
      },
      {
        "ordinal": 6,
        "name": "gender",
        "type_info": "Text"
      },
      {
        "ordinal": 7,
        "name": "birth_date",
        "type_info": "Date"
      },
      {
        "ordinal": 8,
        "name": "birth_place",
        "type_info": "Text"
      },
      {
        "ordinal": 9,
        "name": "death_date",
        "type_info": "Date"
      },
      {
        "ordinal": 10,
        "name": "notes",
        "type_info": "Text"
      },
      {
        "ordinal": 11,
        "name": "email",
        "type_info": "Text"
      },
      {
        "ordinal": 12,
        "name": "phone",
        "type_info": "Text"
      },
      {
        "ordinal": 13,
        "name": "street",
        "type_info": "Text"
      },
      {
        "ordinal": 14,
        "name": "house_number",
        "type_info": "Text"
      },
      {
        "ordinal": 15,
        "name": "zip",
        "type_info": "Text"
      },
      {
        "ordinal": 16,
        "name": "city",
        "type_info": "Text"
      },
      {
        "ordinal": 17,
        "name": "country",
        "type_info": "Text"
      },
      {
        "ordinal": 18,
        "name": "linked_user_id",
        "type_info": "Uuid"
      },
      {
        "ordinal": 19,
        "name": "created_at",
        "type_info": "Timestamptz"
      },
      {
        "ordinal": 20,
        "name": "updated_at",
        "type_info": "Timestamptz"
      }
    ],
    "parameters": {
      "Left": [
        "Uuid",
        "Text",
        "Text",
        "Text",
        "Text",
        "Text",
        "Date",
        "Text",
        "Date",
        "Text",
        "Text",
        "Text",
        "Text",
        "Text",
        "Text",
        "Text",
        "Text",
        "Uuid"
      ]
    },
    "nullable": [
      false,
      false,
      false,
      false,
      false,
      false,
      false,
      true,
      false,
      true,
      false,
      false,
      false,
      false,
      false,
      false,
      false,
      false,
      true,
      false,
      false
    ]
  },
  "hash": "fb35891c9e0ec1e6b535dffd70b38b550542c39940ceafc7f52e5acccebb4e26"
}
